MANIFEST.in
README.rst
json_reference.py
setup.py
test.py
json_reference.egg-info/PKG-INFO
json_reference.egg-info/SOURCES.txt
json_reference.egg-info/dependency_links.txt
json_reference.egg-info/requires.txt
json_reference.egg-info/top_level.txt