Metadata-Version: 1.0
Name: json-reference
Version: 0.1.0
Summary: Simple implementation of the json-reference spec
Home-page: https://bitbucket.org/eodolphi/json-reference/
Author: Ernst Odolphi
Author-email: ernst.odolphi@gmail.com
License: UNKNOWN
Platform: UNKNOWN
